remnawave/__init__.py
remnawave/controllers/__init__.py
remnawave/controllers/api_tokens_management.py
remnawave/controllers/auth.py
remnawave/controllers/bandwidthstats.py
remnawave/controllers/config_profiles.py
remnawave/controllers/external_squads.py
remnawave/controllers/hosts.py
remnawave/controllers/hosts_bulk_actions.py
remnawave/controllers/hwid.py
remnawave/controllers/inbounds.py
remnawave/controllers/inbounds_bulk_actions.py
remnawave/controllers/infra_billing.py
remnawave/controllers/internal_squads.py
remnawave/controllers/keygen.py
remnawave/controllers/nodes.py
remnawave/controllers/nodes_usage_history.py
remnawave/controllers/passkeys.py
remnawave/controllers/remnawave_settings.py
remnawave/controllers/snippets.py
remnawave/controllers/subscription.py
remnawave/controllers/subscription_page.py
remnawave/controllers/subscriptions_controller.py
remnawave/controllers/subscriptions_request.py
remnawave/controllers/subscriptions_settings.py
remnawave/controllers/subscriptions_template.py
remnawave/controllers/system.py
remnawave/controllers/users.py
remnawave/controllers/users_bulk_actions.py
remnawave/controllers/users_stats.py
remnawave/controllers/webhooks.py
remnawave/controllers/xray_config.py
remnawave/enums/__init__.py
remnawave/enums/alpn.py
remnawave/enums/auth.py
remnawave/enums/client_type.py
remnawave/enums/error_code.py
remnawave/enums/fingerprint.py
remnawave/enums/security_layer.py
remnawave/enums/subscriptions_settings.py
remnawave/enums/template_type.py
remnawave/enums/users.py
remnawave/enums/webhook.py
remnawave/exceptions/__init__.py
remnawave/exceptions/general.py
remnawave/exceptions/handler.py
remnawave/models/__init__.py
remnawave/models/api_tokens_management.py
remnawave/models/auth.py
remnawave/models/bandwidthstats.py
remnawave/models/config_profiles.py
remnawave/models/external_squads.py
remnawave/models/hosts.py
remnawave/models/hosts_bulk_actions.py
remnawave/models/hwid.py
remnawave/models/inbounds.py
remnawave-2.4.4.dist-info/METADATA
remnawave-2.4.4.dist-info/WHEEL
remnawave-2.4.4.dist-info/licenses/LICENSE
remnawave-2.4.4.dist-info/RECORD
